prerequisites/__init__.py
prerequisites/py.typed
prerequisites-1.0.4.dist-info/METADATA
prerequisites-1.0.4.dist-info/WHEEL
prerequisites-1.0.4.dist-info/licenses/LICENSE.md
prerequisites-1.0.4.dist-info/RECORD
