Metadata-Version: 2.4
Name: prerequisites
Version: 1.0.4
Summary: Prerequisite functions to help and assert inputs and outputs condition and type
Author: SamuelNLP
License-File: LICENSE.md
Requires-Python: >=3.10
Provides-Extra: dev
Requires-Dist: mypy; extra == 'dev'
Requires-Dist: pre-commit; extra == 'dev'
Requires-Dist: pytest; extra == 'dev'
Requires-Dist: pytest-cov; extra == 'dev'
Requires-Dist: ruff; extra == 'dev'
Requires-Dist: twine; extra == 'dev'
